bits/__init__.py
bits/gcf/__init__.py
bits_gcf-1.8.1.dist-info/METADATA
bits_gcf-1.8.1.dist-info/WHEEL
bits_gcf-1.8.1.dist-info/top_level.txt
bits_gcf-1.8.1.dist-info/RECORD
