Metadata-Version: 2.1
Name: bits-gcf
Version: 1.8.1
Summary: BITS GCF
Home-page: UNKNOWN
Author: Lukas Karlsson
Author-email: karlsson@broadinstitute.org
License: Apache Software License
Platform: UNKNOWN
Requires-Dist: google-cloud-datastore
Requires-Dist: google-cloud-firestore
Requires-Dist: google-cloud-pubsub
Requires-Dist: google-cloud-storage
